promptfoo/__init__.py
promptfoo/cli.py
promptfoo/environment.py
promptfoo/instructions.py
promptfoo/telemetry.py
promptfoo-0.1.2.dist-info/METADATA
promptfoo-0.1.2.dist-info/WHEEL
promptfoo-0.1.2.dist-info/entry_points.txt
promptfoo-0.1.2.dist-info/licenses/LICENSE
promptfoo-0.1.2.dist-info/RECORD
