Metadata-Version: 2.4
Name: promptfoo
Version: 0.1.2
Summary: Python wrapper for the promptfoo CLI - LLM testing, red teaming, and security evaluation
Project-URL: Repository, https://github.com/promptfoo/promptfoo-python
Project-URL: Homepage, https://www.promptfoo.dev
Project-URL: Documentation, https://www.promptfoo.dev/docs
Author-email: Ian Webster <ian@promptfoo.dev>
License: MIT
License-File: LICENSE
Keywords: ai,evaluation,llm,promptfoo,red-team,security,testing
Classifier: Development Status :: 4 - Beta
Classifier: Intended Audience :: Developers
Classifier: License :: OSI Approved :: MIT License
Classifier: Operating System :: OS Independent
Classifier: Programming Language :: Python :: 3
Classifier: Programming Language :: Python :: 3.9
Classifier: Programming Language :: Python :: 3.10
Classifier: Programming Language :: Python :: 3.11
Classifier: Programming Language :: Python :: 3.12
Classifier: Programming Language :: Python :: 3.13
Classifier: Topic :: Scientific/Engineering :: Artificial Intelligence
Classifier: Topic :: Security
Classifier: Topic :: Software Development :: Testing
Requires-Python: >=3.9
Requires-Dist: posthog>=3.0.0
Requires-Dist: pyyaml>=6.0.0
Provides-Extra: dev
Requires-Dist: mypy>=1.16.0; extra == 'dev'
Requires-Dist: pyright>=1.1.400; extra == 'dev'
Requires-Dist: pytest>=8.4.0; extra == 'dev'
Requires-Dist: ruff>=0.12.0; extra == 'dev'
Requires-Dist: types-pyyaml>=6.0.0; extra == 'dev'
